[{"user":"melody-sy","uid":108189592,"date":"August 6, 2023","title":"hellosy! it&apos;s-a-me","post":"hellosy! i&apos;m melody, gaehive manager and resident digital snakegirl! ambitious creativity is my thing-- i love telling huge winding stories through the medium of video games, but here, i think i&apos;m going to be writing short bite-sized slice of life stories set in the worlds i&apos;ve created :&gt;\n&lt;br&gt;&lt;br&gt;that being said, i currently have no ideas-- writer&apos;s block is a pain... i do hope you&apos;re looking forward to what i might whip up in the future, though &gt;.&gt;","id":10,"like":8,"likeby":["F1nn_on_paws","Spacey_boy","-_Mag0-l0rr-86_-","ICantCallNow","livid---liam","IatetocIass","warrior1785","--b-a-s-i-l--"],"love":17,"loveby":["latetothepartyy","furbiez-0-clock","1-o-v-e","embXR_THEauthZr","lesbian-lucifer","F1nn_on_paws","MossIsQueer","HungarianHorntail7","LegoManiac04","Soaring-Jay","dancinqq-","Prague_may23rd1618","ARCHlVED","livid---liam","PrincessMeta","Amazing_Enby","IatetocIass"],"wow":2,"wowby":["livid---liam","IatetocIass"],"yay":4,"yayby":["embXR_THEauthZr","livid---liam","Amazing_Enby","IatetocIass"],"laugh":1,"laughby":["livid---liam"],"sad":3,"sadby":["lesbiandragons","Homo-sec-shoe-whale","livid---liam"]}]