[{"user":"LegoManiac04","uid":21629747,"date":"August 7, 2023","title":"Updates &amp; What&apos;s Next :cool:","post":"&lt;b&gt;What&apos;s new:&lt;/b&gt;&lt;ul&gt;&lt;li&gt;Fixed an issue where users would be stuck at the &quot;Logging In&quot; page.&lt;/li&gt;&lt;li&gt;Redid the login systems slightly, may be a bit quicker now!&lt;/li&gt;&lt;li&gt;Added  new &quot;Feedback&quot; button.&lt;/li&gt;&lt;li&gt;Added reminder that Hivezine posts must also follow Gaehive Studio Guidelines.&lt;/li&gt;&lt;/ul&gt;&lt;br&gt;&lt;b&gt;What&apos;s Next:&lt;/b&gt;&lt;ul&gt;&lt;li&gt;Address issue with API that fetches Hivezine posts failing to fetch all replies.&lt;/li&gt;&lt;li&gt;Add saving system for Hivezine drafts.&lt;/li&gt;&lt;/ul&gt;&lt;br&gt;Cheers! :heart:","id":45,"love":2,"loveby":["livid---liam","MossIsQueer"],"yay":2,"yayby":["livid---liam","Soaring-Jay"],"like":5,"likeby":["Prague_may23rd1618","64Bitzzz","ARCHlVED","dancinqq-","LGBTQIAlex"],"sad":1,"sadby":["lesbiandragons"]}]