[{"user":"ARandomNumberIs7482","uid":106188158,"date":"August 9, 2023","title":"tab poll :flushed:","post":"If you have less than 50 tabs open, click the heart emoji. If you have 50-100 tabs open, click the thumbs-up emoji. If you have 100-200 tabs open, click the crying laughing emoji. If you have 200-300 tabs open, click the shocked emoji. If you have 300-400 tabs open, click the sad emoji. If you have 400-500 tabs open, click the party popper emoji. If you have more than 500 tabs open, click the frog emoji. :frog :frog:","id":91,"laugh":2,"laughby":["ICantCallNow","ARandomNumberIs7482"],"love":17,"loveby":["ICantCallNow","livid---liam","Prague_may23rd1618","coral4444","CreateFrog","ARCHlVED","Scuppy-Lover","lesbian-lucifer","AnotherRandoPerson","dancinqq-","Mossheart29","Moonwatcher127","warrior1785","flying-away","-Lotus-Eater-","LegoManiac04","Amazing_Enby"],"frog":5,"frogby":["memorysauce","MossIsQueer","ICantCallNow","Lavender_lillypad","eve-mii"],"sad":2,"sadby":["ICantCallNow","lesbiandragons"],"yay":1,"yayby":["ICantCallNow"],"wow":1,"wowby":["ICantCallNow"],"like":1,"likeby":["ICantCallNow"]}]